phy_imports_resolver/__init__.py
phy_imports_resolver/__main__.py
phy_imports_resolver/_extractor.py
phy_imports_resolver/cli.py
phy_imports_resolver/imports.gram
phy_imports_resolver/resolver.py
phy_imports_resolver/types.py
phy_imports_resolver-0.3.1.dist-info/METADATA
phy_imports_resolver-0.3.1.dist-info/WHEEL
phy_imports_resolver-0.3.1.dist-info/entry_points.txt
phy_imports_resolver-0.3.1.dist-info/RECORD
