Metadata-Version: 2.4
Name: phy-imports-resolver
Version: 0.3.1
Summary: Resolve imports of a python file or module, with site packages & builtin modules excluded.
License: MIT
Author: Alfred DU
Author-email: ihearmywords@hotmail.com
Requires-Python: >=3.10, <4
Classifier: License :: OSI Approved :: MIT License
Classifier: Programming Language :: Python :: 3
Classifier: Programming Language :: Python :: 3.10
Classifier: Programming Language :: Python :: 3.11
Classifier: Programming Language :: Python :: 3.12
Classifier: Programming Language :: Python :: 3.13
Classifier: Programming Language :: Python :: 3.14
Provides-Extra: cli
Requires-Dist: click ; extra == "cli"
Requires-Dist: graphviz ; extra == "cli"
Project-URL: Homepage, https://github.com/phy-precompiler/imports-resolver
Project-URL: Issues, https://github.com/phy-precompiler/imports-resolver/issues
Project-URL: Repository, https://github.com/phy-precompiler/imports-resolver
